pypom_form/__init__.py
pypom_form/form.py
pypom_form/meta.py
pypom_form/widgets.py
pypom_form/tests/__init__.py
pypom_form/tests/conftest.py
pypom_form/tests/test_meta.py
pypom_form/tests/test_widgets.py
pypom_form-0.1.0.dist-info/DESCRIPTION.rst
pypom_form-0.1.0.dist-info/METADATA
pypom_form-0.1.0.dist-info/RECORD
pypom_form-0.1.0.dist-info/WHEEL
pypom_form-0.1.0.dist-info/entry_points.txt
pypom_form-0.1.0.dist-info/metadata.json
pypom_form-0.1.0.dist-info/top_level.txt
