Metadata-Version: 2.0
Name: pypom-form
Version: 0.1.0
Summary: pypom_form
Home-page: http://pypom-form.readthedocs.io/en/latest/
Author: Tierra QA Team
Author-email: DLQA@tierratelematics.com
License: Apache License, Version 2.0
Platform: UNKNOWN
Classifier: Programming Language :: Python
Classifier: Programming Language :: Python :: 2.7
Classifier: Programming Language :: Python :: 3.5
Classifier: Framework :: Pytest
Classifier: Topic :: Software Development :: Testing
Classifier: License :: OSI Approved :: Apache Software License
Requires-Dist: PyPOM[splinter] (>=1.1.1)
Requires-Dist: colander
Provides-Extra: docs
Requires-Dist: Sphinx; extra == 'docs'
Requires-Dist: sphinx-rtd-theme; extra == 'docs'
Provides-Extra: tests
Requires-Dist: tox; extra == 'tests'
Requires-Dist: pytest-cov; extra == 'tests'
Requires-Dist: mock; extra == 'tests'
